AppiumLibrary/__init__.py
AppiumLibrary/version.py
AppiumLibrary/keywords/__init__.py
AppiumLibrary/keywords/_android_utils.py
AppiumLibrary/keywords/_applicationmanagement.py
AppiumLibrary/keywords/_element.py
AppiumLibrary/keywords/_keyevent.py
AppiumLibrary/keywords/_logging.py
AppiumLibrary/keywords/_runonfailure.py
AppiumLibrary/keywords/_screenrecord.py
AppiumLibrary/keywords/_screenshot.py
AppiumLibrary/keywords/_touch.py
AppiumLibrary/keywords/_waiting.py
AppiumLibrary/keywords/keywordgroup.py
AppiumLibrary/locators/__init__.py
AppiumLibrary/locators/elementfinder.py
AppiumLibrary/utils/__init__.py
AppiumLibrary/utils/applicationcache.py
robotframework_appiumlibrary-3.2.dist-info/licenses/LICENSE
tests/keywords/test_androidUtils.py
tests/keywords/test_applicationmanagement.py
tests/keywords/test_multipleAppiumConnections.py
tests/keywords/webdriverremotemock.py
tests/locators/test_elementfinder.py
tests/unit/kitchen_bytes.py
tests/utils/test_applicationcache.py
robotframework_appiumlibrary-3.2.dist-info/METADATA
robotframework_appiumlibrary-3.2.dist-info/WHEEL
robotframework_appiumlibrary-3.2.dist-info/top_level.txt
robotframework_appiumlibrary-3.2.dist-info/RECORD
