Metadata-Version: 2.4
Name: robotframework-appiumlibrary
Version: 3.2
Summary: Robot Framework Mobile app testing library for Appium Client Android & iOS & Web
Author: MarketSquare - Robot Framework community, William Zhang, Serhat Bolsu
Maintainer-email: Gabriela Simion <gabriela28simion@gmail.com>, Christoph Singer <ch_singer@me.com>, Ed Manlove <emanlove@verizon.net>
License-Expression: Apache-2.0
Project-URL: Homepage, https://github.com/serhatbolsu/robotframework-appiumlibrary
Project-URL: Documentation, https://github.com/serhatbolsu/robotframework-appiumlibrary?tab=readme-ov-file#appium-library-for-robotframework
Project-URL: Changelog, https://github.com/serhatbolsu/robotframework-appiumlibrary/blob/master/CHANGES.rst
Keywords: robotframework,testing,testautomation,mobile,appium,webdriver,app,android,ios
Classifier: Development Status :: 5 - Production/Stable
Classifier: Operating System :: OS Independent
Classifier: Programming Language :: Python
Classifier: Topic :: Software Development :: Quality Assurance
Classifier: Topic :: Software Development :: Testing
Classifier: Programming Language :: Python
Classifier: Programming Language :: Python :: 3.9
Classifier: Programming Language :: Python :: 3.10
Classifier: Programming Language :: Python :: 3.11
Classifier: Programming Language :: Python :: 3.12
Classifier: Programming Language :: Python :: 3.13
Classifier: Framework :: Robot Framework
Classifier: Framework :: Robot Framework :: Library
License-File: LICENSE
Requires-Dist: decorator>=3.3.2
Requires-Dist: robotframework>=2.6.0
Requires-Dist: docutils>=0.8.1
Requires-Dist: selenium>=4.26.0
Requires-Dist: Appium-Python-Client>=5.1.1
Requires-Dist: six>=1.10.0
Requires-Dist: geopy>=2.4.1
Dynamic: license-file
